LICENSE.txt
MANIFEST.in
README.md
setup.cfg
setup.py
imagetyperzapi3/imagetyperzapi.py
imagetyperzapi3.egg-info/PKG-INFO
imagetyperzapi3.egg-info/SOURCES.txt
imagetyperzapi3.egg-info/dependency_links.txt
imagetyperzapi3.egg-info/requires.txt
imagetyperzapi3.egg-info/top_level.txt