Metadata-Version: 1.2
Name: imagetyperzapi3
Version: 0.3
Summary: ImagetyperzAPI Python3 - is a super easy to use bypass captcha API wrapper for imagetyperz.com captcha service
Home-page: https://github.com/imagetyperz-api/imagetyperz-api-python3
Author: Imagetyperz Dev
Author-email: imagetyperz@gmail.com
License: MIT
Download-URL: https://github.com/imagetyperz-api/imagetyperz-api-python3/archive/0.1.tar.gz
Keywords: captcha,bypasscaptcha,decaptcher,decaptcha,2captcha,deathbycaptcha,anticaptcha,bypass recaptcha v2,bypass no captcha recaptcha,bypass invisible recaptcha,captcha services for recaptcha v2,recaptcha v2 captcha solver,google recaptcha solver,recaptcha solver python,recaptcha bypass script
Platform: UNKNOWN
Requires-Python: ==3.*
